colorise_terminal/__init__.py
colorise_terminal/colorise_terminal.py
colorise_terminal/colors_dict.pkl
colorise_terminal/rgb.py
colorise_terminal/data_transformation/__init__.py
colorise_terminal/data_transformation/data_transformation.py
colorise_terminal/tests/__init__.py
colorise_terminal/tests/examples.py
colorise_terminal/tests/tests.py
colorise_terminal-0.1.2.dist-info/LICENSE
colorise_terminal-0.1.2.dist-info/METADATA
colorise_terminal-0.1.2.dist-info/WHEEL
colorise_terminal-0.1.2.dist-info/top_level.txt
colorise_terminal-0.1.2.dist-info/RECORD
